dmri_pcconv/__init__.py
dmri_pcconv/bin/__init__.py
dmri_pcconv/core/__init__.py
dmri_pcconv/core/io.py
dmri_pcconv/core/normalisation.py
dmri_pcconv/core/patcher.py
dmri_pcconv/core/prediction.py
dmri_pcconv/core/qspace.py
dmri_pcconv/core/training.py
dmri_pcconv/core/weights.py
dmri_pcconv/core/model/__init__.py
dmri_pcconv/core/model/lightning.py
dmri_pcconv/core/model/pccnn.py
dmri_pcconv/core/model/pccnn_bv.py
dmri_pcconv/core/model/pccnn_bv_sp.py
dmri_pcconv/core/model/pccnn_sp.py
dmri_pcconv/core/model/rcnn.py
dmri_pcconv/core/model/layers/__init__.py
dmri_pcconv/core/model/layers/conv3dlstm.py
dmri_pcconv/core/model/layers/distributed.py
dmri_pcconv/core/model/layers/misc.py
dmri_pcconv/core/model/layers/pcconv.py
dmri_pcconv/core/model/layers/pcconv_bv.py
dmri_pcconv/core/model/layers/pcconv_bv_sp.py
dmri_pcconv/core/model/layers/pcconv_sp.py
dmri_pcconv/core/model/layers/weightnet.py
dmri_pcconv/core/utils/__init__.py
dmri_pcconv/core/utils/padding.py
dmri_pcconv/core/utils/sphere.py
dmri_pcconv/core/utils/tensor.py
dmri_pcconv-1.0.0.dist-info/LICENSE
dmri_pcconv-1.0.0.dist-info/METADATA
dmri_pcconv-1.0.0.dist-info/WHEEL
dmri_pcconv-1.0.0.dist-info/top_level.txt
dmri_pcconv-1.0.0.dist-info/RECORD
