Metadata-Version: 2.1
Name: dmri-pcconv
Version: 1.0.0
Summary: Parametric Continuous Convolution framework used for Diffusion MRI.
Author: Matthew Lyon
Author-email: matthewlyon18@gmail.com
License: MIT License
Keywords: ai,cv,computer-vision,mri,dmri,super-resolution,cnn,pcconv
Classifier: Programming Language :: Python
Classifier: Operating System :: Unix
Classifier: Operating System :: MacOS
Requires-Python: >=3.8
License-File: LICENSE
Requires-Dist: torch
Requires-Dist: lightning
Requires-Dist: npy-patcher
Requires-Dist: einops
Requires-Dist: nibabel
